{
  "sources": [
    {
      "title": "Twitter @Elon Musk",
      "feedUrl": "https://rsshub.app/twitter/user/elonmusk",
      "siteUrl": "https://twitter.com/elonmusk",
      "articles": [
        {
          "id": "https://twitter.com/elonmusk/status/1608191997768265728",
          "author": "Elon Musk",
          "description": "Re @dogeofficialceo Accurate lol",
          "link": "https://twitter.com/elonmusk/status/1608191997768265728",
          "publishedOn": "2022-12-28T20:03:45.000Z",
          "wordCount": 470,
          "title": "Re @dogeofficialceo Accurate lol",
          "imageUrl": null
        },
        {
          "id": "https://twitter.com/elonmusk/status/1608191667852709889",
          "author": "Elon Musk",
          "description": "Re @BillFOXLA Whoa",
          "link": "https://twitter.com/elonmusk/status/1608191667852709889",
          "publishedOn": "2022-12-28T20:02:27.000Z",
          "wordCount": 470,
          "title": "Re @BillFOXLA Whoa",
          "imageUrl": null
        },
        {
          "id": "https://twitter.com/elonmusk/status/1608188826291167242",
          "author": "Elon Musk",
          "description": "",
          "link": "https://twitter.com/elonmusk/status/1608188826291167242",
          "publishedOn": "2022-12-28T19:51:09.000Z",
          "wordCount": 470,
          "title": "Untitled",
          "imageUrl": null
        },
        {
          "id": "https://twitter.com/elonmusk/status/1608188746947493889",
          "author": "Elon Musk",
          "description": "Re @dogeofficialceo @GadSaad 🤣",
          "link": "https://twitter.com/elonmusk/status/1608188746947493889",
          "publishedOn": "2022-12-28T19:50:50.000Z",
          "wordCount": 470,
          "title": "Re @dogeofficialceo @GadSaad 🤣",
          "imageUrl": null
        },
        {
          "id": "https://twitter.com/elonmusk/status/1608188169417023488",
          "author": "Elon Musk",
          "description": "Re @GadSaad Anyone who says that questioning them is questioning science itself cannot be regarded as a scientist",
          "link": "https://twitter.com/elonmusk/status/1608188169417023488",
          "publishedOn": "2022-12-28T19:48:32.000Z",
          "wordCount": 470,
          "title": "Re @GadSaad Anyone who says that questioning them is questioning science itself cannot be regarded as a scientist",
          "imageUrl": null
        },
        {
          "id": "https://twitter.com/elonmusk/status/1608187489205817345",
          "author": "Elon Musk",
          "description": "Re @GadSaad 🤣🤣🔥🔥",
          "link": "https://twitter.com/elonmusk/status/1608187489205817345",
          "publishedOn": "2022-12-28T19:45:50.000Z",
          "wordCount": 470,
          "title": "Re @GadSaad 🤣🤣🔥🔥",
          "imageUrl": null
        },
        {
          "id": "https://twitter.com/elonmusk/status/1608185734535720960",
          "author": "Elon Musk",
          "description": "Re @mysteriouskat 🎯",
          "link": "https://twitter.com/elonmusk/status/1608185734535720960",
          "publishedOn": "2022-12-28T19:38:52.000Z",
          "wordCount": 470,
          "title": "Re @mysteriouskat 🎯",
          "imageUrl": null
        },
        {
          "id": "https://twitter.com/elonmusk/status/1608175680407191552",
          "author": "Elon Musk",
          "description": "New Twitter policy is to follow the science, which necessarily includes reasoned questioning of the science",
          "link": "https://twitter.com/elonmusk/status/1608175680407191552",
          "publishedOn": "2022-12-28T18:58:55.000Z",
          "wordCount": 470,
          "title": "New Twitter policy is to follow the science, which necessarily includes reasoned questioning of the science",
          "imageUrl": null
        },
        {
          "id": "https://twitter.com/elonmusk/status/1608152239859703809",
          "author": "Elon Musk",
          "description": "Re @PeterDiamandis Synthetic mRNA has incredible potential!",
          "link": "https://twitter.com/elonmusk/status/1608152239859703809",
          "publishedOn": "2022-12-28T17:25:46.000Z",
          "wordCount": 470,
          "title": "Re @PeterDiamandis Synthetic mRNA has incredible potential!",
          "imageUrl": null
        },
        {
          "id": "https://twitter.com/elonmusk/status/1608145311347707905",
          "author": "Elon Musk",
          "description": "They did it!\nElon Musk: SpaceX Falcon 🚀 team is making excellent progress – aiming for 60 launches this year!",
          "link": "https://twitter.com/elonmusk/status/1608145311347707905",
          "publishedOn": "2022-12-28T16:58:14.000Z",
          "wordCount": 470,
          "title": "They did it!",
          "imageUrl": null
        },
        {
          "id": "https://twitter.com/elonmusk/status/1608143077910233098",
          "author": "Elon Musk",
          "description": "Re @sevensixfive @DanielleFong I’m not cis, you are",
          "link": "https://twitter.com/elonmusk/status/1608143077910233098",
          "publishedOn": "2022-12-28T16:49:22.000Z",
          "wordCount": 470,
          "title": "Re @sevensixfive @DanielleFong I’m not cis, you are",
          "imageUrl": null
        },
        {
          "id": "https://twitter.com/elonmusk/status/1608134412981469187",
          "author": "Elon Musk",
          "description": "Re @TheBabylonBee 🤣🤣",
          "link": "https://twitter.com/elonmusk/status/1608134412981469187",
          "publishedOn": "2022-12-28T16:14:56.000Z",
          "wordCount": 470,
          "title": "Re @TheBabylonBee 🤣🤣",
          "imageUrl": null
        },
        {
          "id": "https://twitter.com/elonmusk/status/1608129808042496001",
          "author": "Elon Musk",
          "description": "Re @PeterDiamandis The AIs will write each other lots of emails!",
          "link": "https://twitter.com/elonmusk/status/1608129808042496001",
          "publishedOn": "2022-12-28T15:56:38.000Z",
          "wordCount": 470,
          "title": "Re @PeterDiamandis The AIs will write each other lots of emails!",
          "imageUrl": null
        },
        {
          "id": "https://twitter.com/elonmusk/status/1608128979839471616",
          "author": "Elon Musk",
          "description": "Re @DanielleFong Yeah, I’m not a fan of pronouns when someone is giving every possible visual cue for he or she, but then still insists on telling you exactly what you expect. \nI do support pronouns that aren’t completely obvious based on visual cues.",
          "link": "https://twitter.com/elonmusk/status/1608128979839471616",
          "publishedOn": "2022-12-28T15:53:21.000Z",
          "wordCount": 470,
          "title": "Re @DanielleFong Yeah, I’m not a fan of pronouns when someone is giving every possible visual cue for he or she, but then still insists on telling yo...",
          "imageUrl": null
        },
        {
          "id": "https://twitter.com/elonmusk/status/1608124721132105733",
          "author": "Elon Musk",
          "description": "Re @Z3RO_Y34R @pmarca “Gain-of-function” should be called “bioweapon” research, as the function referred is death! \nWhat was the name changed to this time?",
          "link": "https://twitter.com/elonmusk/status/1608124721132105733",
          "publishedOn": "2022-12-28T15:36:25.000Z",
          "wordCount": 470,
          "title": "Re @Z3RO_Y34R @pmarca “Gain-of-function” should be called “bioweapon” research, as the function referred is death! What was the name changed to th...",
          "imageUrl": null
        },
        {
          "id": "https://twitter.com/elonmusk/status/1608118870107209728",
          "author": "Elon Musk",
          "description": "Congratulations SpaceX Falcon team on 60 successful launches this year!!\nSpaceX: Falcon 9 launches 54 Starlink satellites to low-Earth orbit; completes SpaceX’s 60th mission of 2022!",
          "link": "https://twitter.com/elonmusk/status/1608118870107209728",
          "publishedOn": "2022-12-28T15:13:10.000Z",
          "wordCount": 470,
          "title": "Congratulations SpaceX Falcon team on 60 successful launches this year!!",
          "imageUrl": null
        },
        {
          "id": "https://twitter.com/elonmusk/status/1608041896525307904",
          "author": "Elon Musk",
          "description": "Re @stillgray Free phones to report themselves and they never even call to say hi 😢",
          "link": "https://twitter.com/elonmusk/status/1608041896525307904",
          "publishedOn": "2022-12-28T10:07:18.000Z",
          "wordCount": 470,
          "title": "Re @stillgray Free phones to report themselves and they never even call to say hi 😢",
          "imageUrl": null
        },
        {
          "id": "https://twitter.com/elonmusk/status/1608037865073643520",
          "author": "Elon Musk",
          "description": "Re @JohnnaCrider1 Agreed",
          "link": "https://twitter.com/elonmusk/status/1608037865073643520",
          "publishedOn": "2022-12-28T09:51:17.000Z",
          "wordCount": 470,
          "title": "Re @JohnnaCrider1 Agreed",
          "imageUrl": null
        },
        {
          "id": "https://twitter.com/elonmusk/status/1608037483140325377",
          "author": "Elon Musk",
          "description": "Re @stillgray Really?",
          "link": "https://twitter.com/elonmusk/status/1608037483140325377",
          "publishedOn": "2022-12-28T09:49:46.000Z",
          "wordCount": 470,
          "title": "Re @stillgray Really?",
          "imageUrl": null
        },
        {
          "id": "https://twitter.com/SpaceX/status/1608036003251621888",
          "author": "Elon Musk",
          "description": "RT SpaceX\nFalcon 9’s first stage has landed on the A Shortfall of Gravitas droneship",
          "link": "https://twitter.com/SpaceX/status/1608036003251621888",
          "publishedOn": "2022-12-28T09:43:53.000Z",
          "wordCount": 470,
          "title": "RT SpaceX: Falcon 9’s first stage has landed on the A Shortfall of Gravitas droneship",
          "imageUrl": null
        }
      ]
    }
  ],
  "cliVersion": "1.15.1"
}